[
  {
    "context_length": 128,
    "method": "Baseline",
    "ttft_ms": 4.814099999748578,
    "tpot_ms": 4.384761279462733,
    "throughput": 227.99974632617202,
    "kv_mb": 5.3203125,
    "total_gflops": 9.0273792,
    "avg_gflops_per_tok": 0.03959376842105263,
    "num_gen": 100,
    "ttft_std": 0.2669792692409797,
    "tput_std": 7.3409327117612735,
    "speedup": 1.0,
    "kv_reduction_%": 0.0,
    "flops_reduction_%": 0.0
  },
  {
    "context_length": 128,
    "method": "CLE-Light  (-20%KV)",
    "ttft_ms": 5.389833332931933,
    "tpot_ms": 4.31274478114727,
    "throughput": 231.2937949356594,
    "kv_mb": 4.7109375,
    "total_gflops": 8.9954304,
    "avg_gflops_per_tok": 0.039453642105263156,
    "num_gen": 100,
    "ttft_std": 0.6821830423225045,
    "tput_std": 0.4336603734491125,
    "speedup": 1.0144,
    "kv_reduction_%": 11.45,
    "flops_reduction_%": 0.35
  },
  {
    "context_length": 128,
    "method": "CLE-Medium (-50%KV)",
    "ttft_ms": 5.062100000031933,
    "tpot_ms": 4.289399663296594,
    "throughput": 232.76113491672947,
    "kv_mb": 3.8203125,
    "total_gflops": 8.948736,
    "avg_gflops_per_tok": 0.03924884210526316,
    "num_gen": 100,
    "ttft_std": 0.34798660872392995,
    "tput_std": 4.0925941852486805,
    "speedup": 1.0209,
    "kv_reduction_%": 28.19,
    "flops_reduction_%": 0.87
  },
  {
    "context_length": 128,
    "method": "CLE-Heavy  (-70%KV)",
    "ttft_ms": 5.390500000127456,
    "tpot_ms": 4.368315488212988,
    "throughput": 228.40603921395552,
    "kv_mb": 3.2109375,
    "total_gflops": 8.9167872,
    "avg_gflops_per_tok": 0.03910871578947368,
    "num_gen": 100,
    "ttft_std": 0.4264085838000139,
    "tput_std": 2.568400183758244,
    "speedup": 1.0018,
    "kv_reduction_%": 39.65,
    "flops_reduction_%": 1.23
  },
  {
    "context_length": 256,
    "method": "Baseline",
    "ttft_ms": 5.347233333244124,
    "tpot_ms": 4.307579124576511,
    "throughput": 231.63243102901464,
    "kv_mb": 8.3203125,
    "total_gflops": 14.620483584,
    "avg_gflops_per_tok": 0.041068774112359555,
    "num_gen": 100,
    "ttft_std": 0.15389835429370682,
    "tput_std": 3.824686616657985,
    "speedup": 1.0,
    "kv_reduction_%": 0.0,
    "flops_reduction_%": 0.0
  },
  {
    "context_length": 256,
    "method": "CLE-Light  (-20%KV)",
    "ttft_ms": 6.488266666565323,
    "tpot_ms": 4.344164983164164,
    "throughput": 229.0639986060518,
    "kv_mb": 7.1015625,
    "total_gflops": 14.556585984,
    "avg_gflops_per_tok": 0.04088928647191011,
    "num_gen": 100,
    "ttft_std": 0.5595423160566855,
    "tput_std": 0.4993430612099817,
    "speedup": 0.9889,
    "kv_reduction_%": 14.65,
    "flops_reduction_%": 0.44
  },
  {
    "context_length": 256,
    "method": "CLE-Medium (-50%KV)",
    "ttft_ms": 5.804999999782012,
    "tpot_ms": 4.265680134683782,
    "throughput": 233.60969058194115,
    "kv_mb": 5.3203125,
    "total_gflops": 14.463197184,
    "avg_gflops_per_tok": 0.040626958382022474,
    "num_gen": 100,
    "ttft_std": 0.17360552979383181,
    "tput_std": 2.8592069065286783,
    "speedup": 1.0085,
    "kv_reduction_%": 36.06,
    "flops_reduction_%": 1.08
  },
  {
    "context_length": 256,
    "method": "CLE-Heavy  (-70%KV)",
    "ttft_ms": 5.733333333409973,
    "tpot_ms": 4.304570707072435,
    "throughput": 231.62403154319017,
    "kv_mb": 4.1015625,
    "total_gflops": 14.399299584,
    "avg_gflops_per_tok": 0.04044747074157303,
    "num_gen": 100,
    "ttft_std": 0.19364618076853027,
    "tput_std": 5.311490518645407,
    "speedup": 1.0,
    "kv_reduction_%": 50.7,
    "flops_reduction_%": 1.51
  },
  {
    "context_length": 512,
    "method": "Baseline",
    "ttft_ms": 8.32050000038483,
    "tpot_ms": 4.0731404040355725,
    "throughput": 242.99671939817222,
    "kv_mb": 14.3203125,
    "total_gflops": 27.014651904,
    "avg_gflops_per_tok": 0.044141588078431375,
    "num_gen": 100,
    "ttft_std": 0.21207694359969165,
    "tput_std": 2.6692153801925205,
    "speedup": 1.0,
    "kv_reduction_%": 0.0,
    "flops_reduction_%": 0.0
  },
  {
    "context_length": 512,
    "method": "CLE-Light  (-20%KV)",
    "ttft_ms": 8.52873333315074,
    "tpot_ms": 4.194264983170521,
    "throughput": 235.9897324755296,
    "kv_mb": 11.90625,
    "total_gflops": 26.888085504,
    "avg_gflops_per_tok": 0.04393478023529412,
    "num_gen": 100,
    "ttft_std": 0.14191054722852503,
    "tput_std": 1.6427807152312823,
    "speedup": 0.9712,
    "kv_reduction_%": 16.86,
    "flops_reduction_%": 0.47
  },
  {
    "context_length": 512,
    "method": "CLE-Medium (-50%KV)",
    "ttft_ms": 8.513666666961702,
    "tpot_ms": 4.262038047134852,
    "throughput": 232.39773836823338,
    "kv_mb": 8.3203125,
    "total_gflops": 26.700079104,
    "avg_gflops_per_tok": 0.04362758023529412,
    "num_gen": 100,
    "ttft_std": 0.3056424765117149,
    "tput_std": 5.429292041260863,
    "speedup": 0.9564,
    "kv_reduction_%": 41.9,
    "flops_reduction_%": 1.16
  },
  {
    "context_length": 512,
    "method": "CLE-Heavy  (-70%KV)",
    "ttft_ms": 8.333533333825471,
    "tpot_ms": 4.3746077441052815,
    "throughput": 226.6230864720985,
    "kv_mb": 5.90625,
    "total_gflops": 26.573512704,
    "avg_gflops_per_tok": 0.04342077239215686,
    "num_gen": 100,
    "ttft_std": 0.2567771278345389,
    "tput_std": 5.2766347445790815,
    "speedup": 0.9326,
    "kv_reduction_%": 58.76,
    "flops_reduction_%": 1.63
  },
  {
    "context_length": 1024,
    "method": "Baseline",
    "ttft_ms": 15.31423333320466,
    "tpot_ms": 4.435637037038925,
    "throughput": 220.42145197617893,
    "kv_mb": 26.3203125,
    "total_gflops": 56.634826752,
    "avg_gflops_per_tok": 0.05038685654092527,
    "num_gen": 100,
    "ttft_std": 0.18089168938750705,
    "tput_std": 10.96154514474964,
    "speedup": 1.0,
    "kv_reduction_%": 0.0,
    "flops_reduction_%": 0.0
  },
  {
    "context_length": 1024,
    "method": "CLE-Light  (-20%KV)",
    "ttft_ms": 16.781266666839656,
    "tpot_ms": 4.1138265993287515,
    "throughput": 235.82134126154446,
    "kv_mb": 21.515625,
    "total_gflops": 56.382922752,
    "avg_gflops_per_tok": 0.05016274266192171,
    "num_gen": 100,
    "ttft_std": 0.5946019871423724,
    "tput_std": 0.22980530757775128,
    "speedup": 1.0699,
    "kv_reduction_%": 18.25,
    "flops_reduction_%": 0.44
  },
  {
    "context_length": 1024,
    "method": "CLE-Medium (-50%KV)",
    "ttft_ms": 16.212466666426433,
    "tpot_ms": 4.196720202022757,
    "throughput": 231.65707019878798,
    "kv_mb": 14.3203125,
    "total_gflops": 56.005681152,
    "avg_gflops_per_tok": 0.049827118462633456,
    "num_gen": 100,
    "ttft_std": 0.3233617378237938,
    "tput_std": 1.681421503162709,
    "speedup": 1.051,
    "kv_reduction_%": 45.59,
    "flops_reduction_%": 1.11
  },
  {
    "context_length": 1024,
    "method": "CLE-Heavy  (-70%KV)",
    "ttft_ms": 16.302833333005157,
    "tpot_ms": 4.2605255892260585,
    "throughput": 228.27673422015997,
    "kv_mb": 9.515625,
    "total_gflops": 55.753777152,
    "avg_gflops_per_tok": 0.049603004583629894,
    "num_gen": 100,
    "ttft_std": 0.15587592315385768,
    "tput_std": 2.319241836817448,
    "speedup": 1.0356,
    "kv_reduction_%": 63.85,
    "flops_reduction_%": 1.56
  }
]